setup.cfg
setup.py
mental/__init__.py
mental/demo.py
mental/models.py
mental.egg-info/PKG-INFO
mental.egg-info/SOURCES.txt
mental.egg-info/dependency_links.txt
mental.egg-info/top_level.txt
mental.egg-info/zip-safe