Metadata-Version: 1.1
Name: mental
Version: 0.2.0
Summary: Mental poker implementation
Home-page: https://github.com/colonelmo/mental-poker
Author: Mohammad Nasirifar
Author-email: far.nasiri.m@gmail.com
License: BSD
Download-URL: https://github.com/colonelmo/mental/archive/0.1.0.tar.gz
Keywords: mental poker rsa cryptography
Platform: UNKNOWN
Classifier: Development Status :: 3 - Alpha
Classifier: Environment :: Console
Classifier: Intended Audience :: Developers
Classifier: Operating System :: POSIX :: Linux
Classifier: Programming Language :: Python
